eenhoorntje_llm_lib/__init__.py
eenhoorntje_llm_lib/amazon.py
eenhoorntje_llm_lib/deepl.py
eenhoorntje_llm_lib/edit_distance.py
eenhoorntje_llm_lib/embedding.py
eenhoorntje_llm_lib/gemini.py
eenhoorntje_llm_lib/google.py
eenhoorntje_llm_lib/language_codes.py
eenhoorntje_llm_lib/llm.py
eenhoorntje_llm_lib/llm_cache.py
eenhoorntje_llm_lib/microsoft.py
eenhoorntje_llm_lib/modern_mt.py
eenhoorntje_llm_lib/translate.py
eenhoorntje_llm_lib/translate_llm.py
eenhoorntje_llm_lib/utils.py
eenhoorntje_llm_lib/yandex.py
einhoorntje_llm_lib/__init__.py
einhoorntje_llm_lib/llm.py
einhoorntje_llm_lib/llm_cache.py
eenhoorntje_llm_lib-0.32.dist-info/METADATA
eenhoorntje_llm_lib-0.32.dist-info/WHEEL
eenhoorntje_llm_lib-0.32.dist-info/top_level.txt
eenhoorntje_llm_lib-0.32.dist-info/RECORD
