Metadata-Version: 2.1
Name: eenhoorntje-llm-lib
Version: 0.32
Summary: A lib for cached LLM calling and translation
Author: Dmitrii Lukianov
Author-email: unicornporated@gmail.com
Requires-Dist: openai
Requires-Dist: google-generativeai
Requires-Dist: google-cloud-translate
Requires-Dist: modernmt
Requires-Dist: azure-ai-translation-text ==1.0.0b1
Requires-Dist: boto3
Requires-Dist: pillow
